pymdps-0.1.3.dist-info/METADATA
pymdps-0.1.3.dist-info/WHEEL
pymdps-0.1.3.dist-info/licenses/LICENSE
pymdps/__init__.py
pymdps/_pymdps.cpython-311-darwin.so
pymdps-0.1.3.dist-info/RECORD
