Metadata-Version: 2.4
Name: pymdps
Version: 0.1.3
Classifier: Development Status :: 3 - Alpha
Classifier: Intended Audience :: Science/Research
Classifier: License :: OSI Approved :: MIT License
Classifier: Programming Language :: Python :: 3
Classifier: Programming Language :: Python :: 3.9
Classifier: Programming Language :: Python :: 3.10
Classifier: Programming Language :: Python :: 3.11
Classifier: Programming Language :: Python :: 3.12
Requires-Dist: matplotlib
Requires-Dist: plotly
Requires-Dist: pytest ; extra == 'testing'
Requires-Dist: pytest-cov ; extra == 'testing'
Requires-Dist: pytest-mock ; extra == 'testing'
Requires-Dist: mkdocs-material >=9.5.49 ; extra == 'docs'
Requires-Dist: mkdocstrings[python] >=0.24.0 ; extra == 'docs'
Requires-Dist: mkdocs-git-revision-date-localized-plugin >=1.3.0 ; extra == 'docs'
Requires-Dist: mkdocs-section-index >=0.3.9 ; extra == 'docs'
Requires-Dist: pymdps[testing,docs] ; extra == 'all'
Provides-Extra: testing
Provides-Extra: docs
Provides-Extra: all
License-File: LICENSE
Summary: pymdps is a Python package for working with Markov Decision Processes (MDPs) and
